big_text_tabs/__init__.py
big_text_tabs/example.py
big_text_tabs/frontend/build/asset-manifest.json
big_text_tabs/frontend/build/bootstrap.min.css
big_text_tabs/frontend/build/bootstrap.min.css.map
big_text_tabs/frontend/build/index.html
big_text_tabs/frontend/build/static/css/main.2412a3c6.css
big_text_tabs/frontend/build/static/css/main.2412a3c6.css.map
big_text_tabs/frontend/build/static/js/main.b9729270.js
big_text_tabs/frontend/build/static/js/main.b9729270.js.LICENSE.txt
big_text_tabs/frontend/build/static/js/main.b9729270.js.map
streamlit_big_text_tabs-0.0.4.dist-info/LICENSE
streamlit_big_text_tabs-0.0.4.dist-info/METADATA
streamlit_big_text_tabs-0.0.4.dist-info/WHEEL
streamlit_big_text_tabs-0.0.4.dist-info/top_level.txt
streamlit_big_text_tabs-0.0.4.dist-info/RECORD
